FakeFSHelpers-1.4.0-py3.12-nspkg.pth
schwarz/fakefs_helpers/__init__.py
schwarz/fakefs_helpers/fake_fs.py
schwarz/fakefs_helpers/temp_fs.py
schwarz/fakefs_helpers/utils.py
tests/__init__.py
tests/fake_fs_test.py
tests/temp_fs_test.py
FakeFSHelpers-1.4.0.dist-info/LICENSE.txt
FakeFSHelpers-1.4.0.dist-info/METADATA
FakeFSHelpers-1.4.0.dist-info/WHEEL
FakeFSHelpers-1.4.0.dist-info/namespace_packages.txt
FakeFSHelpers-1.4.0.dist-info/top_level.txt
FakeFSHelpers-1.4.0.dist-info/RECORD
