Metadata-Version: 2.1
Name: FakeFSHelpers
Version: 1.4.0
Summary: convenience library to help working with filesystem-related code in unit tests
Home-page: https://github.com/FelixSchwarz/fakefs_helpers
Author: Felix Schwarz
Author-email: felix.schwarz@oss.schwarz.eu
License: MIT
Project-URL: Code, https://github.com/FelixSchwarz/fakefs_helpers
Project-URL: Issue tracker, https://github.com/FelixSchwarz/fakefs_helpers/issues
Classifier: Development Status :: 5 - Production/Stable
Classifier: Intended Audience :: Developers
Classifier: License :: OSI Approved :: MIT License
Classifier: Programming Language :: Python :: 2
Classifier: Programming Language :: Python :: 2.7
Classifier: Programming Language :: Python :: 3
Classifier: Programming Language :: Python :: 3.6
Classifier: Programming Language :: Python :: 3.7
Classifier: Programming Language :: Python :: 3.8
Classifier: Programming Language :: Python :: 3.9
Classifier: Programming Language :: Python :: 3.10
Classifier: Programming Language :: Python :: 3.11
Requires-Python: !=3.0.*,!=3.1.*,!=3.2.*,!=3.3.*,>=2.7
License-File: LICENSE.txt
Requires-Dist: pyfakefs (>=3.4)
Provides-Extra: testing
Requires-Dist: pathlib2 ; (python_version < "3.0") and extra == 'testing'
